st_clickable_images/__init__.py
st_clickable_images/frontend/build/asset-manifest.json
st_clickable_images/frontend/build/bootstrap.min.css
st_clickable_images/frontend/build/index.html
st_clickable_images/frontend/build/precache-manifest.3ba1b91be2609c7b49743831fdb270d8.js
st_clickable_images/frontend/build/precache-manifest.d31ba4031a270b103725cc704f565447.js
st_clickable_images/frontend/build/service-worker.js
st_clickable_images/frontend/build/static/js/2.1ee3ce4d.chunk.js
st_clickable_images/frontend/build/static/js/2.1ee3ce4d.chunk.js.LICENSE.txt
st_clickable_images/frontend/build/static/js/2.1ee3ce4d.chunk.js.map
st_clickable_images/frontend/build/static/js/main.b47addb1.chunk.js
st_clickable_images/frontend/build/static/js/main.b47addb1.chunk.js.map
st_clickable_images/frontend/build/static/js/main.f55454d2.chunk.js
st_clickable_images/frontend/build/static/js/main.f55454d2.chunk.js.map
st_clickable_images/frontend/build/static/js/runtime-main.11ec9aca.js
st_clickable_images/frontend/build/static/js/runtime-main.11ec9aca.js.map
st_clickable_images-0.0.3.dist-info/LICENSE
st_clickable_images-0.0.3.dist-info/METADATA
st_clickable_images-0.0.3.dist-info/WHEEL
st_clickable_images-0.0.3.dist-info/top_level.txt
st_clickable_images-0.0.3.dist-info/RECORD
