Metadata-Version: 2.1
Name: st-clickable-images
Version: 0.0.3
Summary: A Streamlit component to display clickable images
Home-page: UNKNOWN
Author: 
Author-email: 
License: UNKNOWN
Platform: UNKNOWN
Requires-Python: >=3.6
License-File: LICENSE
